hypertrie/__init__.py
hypertrie/cairo_commons.py
hypertrie/cairo_hypertrie1_context.py
hypertrie/cairo_hypertrie2_context.py
hypertrie/colors.py
hypertrie/draw_hypertrie_context.py
hypertrie/hypertrie1.py
hypertrie/hypertrie2.py
hypertrie/hypertrie_commons.py
hypertrie/draw_hypertrie/__init__.py
hypertrie/draw_hypertrie/run.py
draw_hypertrie-0.1.4.dist-info/LICENSE
draw_hypertrie-0.1.4.dist-info/LICENSE.md
draw_hypertrie-0.1.4.dist-info/METADATA
draw_hypertrie-0.1.4.dist-info/WHEEL
draw_hypertrie-0.1.4.dist-info/entry_points.txt
draw_hypertrie-0.1.4.dist-info/top_level.txt
draw_hypertrie-0.1.4.dist-info/RECORD
