Metadata-Version: 2.1
Name: draw-hypertrie
Version: 0.1.4
Summary: A tool to print hypertrie.
Home-page: https://github.com/dice-group/print_hypertrie
Author: Alexander Bigerl
Author-email: info@dice-research.org
License: AGPL v3
Platform: UNKNOWN
Classifier: Programming Language :: Python :: 3.8
Classifier: License :: OSI Approved :: GNU Affero General Public License v3 or later (AGPLv3+)
Requires-Python: >=3.8
Requires-Dist: Cython (>=0.29.23)
Requires-Dist: pycairo (>=1.20.0)
Requires-Dist: click (>=7.1.2)
